pysumreg/LICENSE.txt
pysumreg/__init__.py
pysumreg/_version.py
pysumreg/sum_registers.py
pysumreg/tests/__init__.py
pysumreg/tests/test_sum_registers.py
pysumreg-1.0.7.dist-info/METADATA
pysumreg-1.0.7.dist-info/WHEEL
pysumreg-1.0.7.dist-info/top_level.txt
pysumreg-1.0.7.dist-info/RECORD
