Metadata-Version: 2.1
Name: pysumreg
Version: 1.0.7
Summary: Statistics of list of (x, y) pairs from calculator-style summation registers.
Author-email: "Pete R. Jemian" <prjemian+pysumreg@gmail.com>
Maintainer-email: Pete Jemian <prjemian+pysumreg@gmail.com>
License: Creative Commons Attribution 4.0 International Public License
Project-URL: Homepage, https://prjemian.github.io/pysumreg/latest/
Project-URL: Bug Tracker, https://github.com/prjemian/pysumreg/issues
Keywords: fitting,linear regression,statistics
Classifier: Development Status :: 6 - Mature
Classifier: Environment :: Console
Classifier: Intended Audience :: Science/Research
Classifier: License :: Freely Distributable
Classifier: License :: Public Domain
Classifier: Programming Language :: Python
Classifier: Programming Language :: Python :: 3
Classifier: Topic :: Scientific/Engineering
Classifier: Topic :: Scientific/Engineering :: Astronomy
Classifier: Topic :: Scientific/Engineering :: Bio-Informatics
Classifier: Topic :: Scientific/Engineering :: Chemistry
Classifier: Topic :: Scientific/Engineering :: Information Analysis
Classifier: Topic :: Scientific/Engineering :: Interface Engine/Protocol Translator
Classifier: Topic :: Scientific/Engineering :: Mathematics
Classifier: Topic :: Scientific/Engineering :: Physics
Classifier: Topic :: Scientific/Engineering :: Visualization
Classifier: Topic :: Software Development
Classifier: Topic :: Utilities
Requires-Python: >=3.8
